journalx/__init__.py
journalx/cli.py
journalx/main.py
journalx-0.0.2.1.dist-info/LICENSE
journalx-0.0.2.1.dist-info/METADATA
journalx-0.0.2.1.dist-info/WHEEL
journalx-0.0.2.1.dist-info/entry_points.txt
journalx-0.0.2.1.dist-info/top_level.txt
journalx-0.0.2.1.dist-info/RECORD
