Metadata-Version: 2.1
Name: journalx
Version: 0.0.2.1
Summary: journalx supercharges your text-based journal
Home-page: https://github.com/altairmn/journalx
Author: Sahil Manocha
Author-email: sahilmanocha1994@gmail.com
License: UNKNOWN
Platform: UNKNOWN
Classifier: Programming Language :: Python :: 3
Classifier: License :: OSI Approved :: MIT License
Classifier: Operating System :: OS Independent
Requires-Python: >=3.6
License-File: LICENSE
Requires-Dist: Click
Requires-Dist: python-frontmatter
